slideception.py
slideception-0.1.0.dist-info/LICENSE
slideception-0.1.0.dist-info/METADATA
slideception-0.1.0.dist-info/WHEEL
slideception-0.1.0.dist-info/top_level.txt
slideception-0.1.0.dist-info/RECORD
