Metadata-Version: 2.1
Name: slideception
Version: 0.1.0
Summary: Framework for interactive slide decks in the terminal
Home-page: https://github.com/kalgynirae/slideception
Author: Colin Chan
Author-email: colinchan@lumeh.org
License: UNKNOWN
Platform: UNKNOWN
Classifier: Development Status :: 3 - Alpha
Classifier: License :: OSI Approved :: MIT License
Classifier: Programming Language :: Python :: 3
Classifier: Programming Language :: Python :: 3.8
Classifier: Topic :: Multimedia :: Graphics :: Presentation
Classifier: Topic :: Terminals
Requires-Python: >=3.8
Requires-Dist: boxing
Requires-Dist: ipython
Requires-Dist: mistletoe
Requires-Dist: Pygments
